{
 "id": "/textsegment",
  "$schema": "http://json-schema.org/draft-04/schema#",
  "title": "TextSegment",
  "description": "A Styled segment of text",
  "type": "object",
  "definitions": {
    "text": {
      "type": "string",
      "description": "The text",
      "example": "Hello World"
    },
  },
  "properties": {
    "text": {
      "$ref": "#/definitions/text"
    },
    "style": {
      "description": "Style being applied to the text",
      "$ref": "./textStyle.json"
    }
  },
  "ypCategory": "Text"
}